_pyk4a
pyk4a
